{
  "@id": "dtmi:com:willowinc:TotalLeavingPeopleCountSensor;1",
  "@type": "Interface",
  "displayName": {
    "en": "Total Leaving People Count Sensor"
  },
  "description": {
    "en": "A totalized count of the number of people leaving a space over a defined period of time. The value continues to increment if the same individual leaves multiple times."
  },
  "extends" : [
    "dtmi:com:willowinc:LeavingPeopleCountSensor;1"
  ],
  "contents": [
    
  ],
  "@context": "dtmi:dtdl:context;2"
}
