{
  "@id": "dtmi:com:willowinc:VariableFrequencyDrive;1",
  "@type": "Interface",
  "displayName": {
    "en": "Variable Frequency Drive"
  },
  "extends" : [
    "dtmi:com:willowinc:MotorController;1"
  ],
  "contents": [
    {
      "@type": "Property",
      "displayName": {
        "en": "type"
      },
      "name": "type",
      "schema": {
        "@type": "Enum",
        "enumValues": [
          {
            "enumValue": "VoltageSourceInverter",
            "name": "VoltageSourceInverter"
          },
          {
            "enumValue": "PulseWidthModulation",
            "name": "PulseWidthModulation"
          },
          {
            "enumValue": "CurrentSourceInverter",
            "name": "CurrentSourceInverter"
          }
        ],
        "valueSchema": "string"
      },
      "writable": true
    }
  ],
  "@context": [
    "dtmi:dtdl:context;3"
  ]
}
