{
  "@id": "dtmi:com:willowinc:PrimaryLoopLeavingCondenserWaterValveOpenActuator;1",
  "@type": "Interface",
  "displayName": {
    "en": "Primary Loop Leaving Condenser Water Valve Open Actuator"
  },
  "description": {"en": "The Boolean command which sets the state of the primary loop leaving condenser water valve to 'open' when 'true'"},
  "extends" : [
    "dtmi:com:willowinc:LeavingCondenserWaterValveOpenActuator;1"
  ],
  "contents": [

  ],
  "@context": [
    "dtmi:dtdl:context;3"
  ]
}
