{
  "@id": "dtmi:com:syyclops:TransferSwitch;1",
  "@type": "Interface",
  "displayName": {
    "en": "Transfer Switch"
  },
  "extends": [
    "dtmi:com:syyclops:ElectricalDistributionEquipment;1"
  ],
  "contents": [
    {
      "@type": "Property",
      "displayName": {
        "en": "Poles"
      },
      "name": "poles",
      "schema": {
        "@type": "Enum",
        "enumValues": [
          {
            "enumValue": "Three",
            "name": "Three",
            "@id": "dtmi:com:syyclops:TransferSwitch:Three;1"
          },
          {
            "enumValue": "Four",
            "name": "Four",
            "@id": "dtmi:com:syyclops:TransferSwitch:Four;1"
          }
        ],
        "valueSchema": "string",
        "@id": "dtmi:com:syyclops:TransferSwitch:ES1;1"
      },
      "writable": true,
      "@id": "dtmi:com:syyclops:TransferSwitch:poles;1"
    },
    {
      "@type": [
        "Current",
        "Property"
      ],
      "displayName": {
        "en": "Mains Rating"
      },
      "name": "mainsRating",
      "schema": "double",
      "unit": "ampere",
      "writable": true
    },
    {
      "@type": "Component",
      "name": "mainBus",
      "displayName": {
        "en": "Main Bus"
      },
      "schema": "dtmi:com:syyclops:ElectricalBus;1",
      "@id": "dtmi:com:syyclops:TransferSwitch:mainBus;1"
    }
  ],
  "@context": [
    "dtmi:dtdl:context;3",
    "dtmi:dtdl:extension:quantitativeTypes;1"
  ]
}