{
  "@id": "dtmi:com:syyclops:TwistedPairCableConnector;1",
  "@type": "Interface",
  "displayName": {
    "en": "Twisted Pair Cable Connector"
  },
  "extends": [
    "dtmi:com:syyclops:TelecommunicationCableConnector;1"
  ],
  "contents": [
    {
      "@type": "Property",
      "name": "categoryRating",
      "displayName": {
        "en": "Category Rating"
      },
      "schema": {
        "@type": "Enum",
        "enumValues": [
          {
            "name": "category3",
            "displayName": {
              "en": "Category 3"
            },
            "enumValue": "Category 3",
            "@id": "dtmi:com:syyclops:TwistedPairCableConnector:category3;1"
          },
          {
            "name": "category5e",
            "displayName": {
              "en": "Category 5e"
            },
            "enumValue": "Category 5e",
            "@id": "dtmi:com:syyclops:TwistedPairCableConnector:category5e;1"
          },
          {
            "name": "category6",
            "displayName": {
              "en": "Category 6"
            },
            "enumValue": "Category 6",
            "@id": "dtmi:com:syyclops:TwistedPairCableConnector:category6;1"
          },
          {
            "name": "category6A",
            "displayName": {
              "en": "Category 6A"
            },
            "enumValue": "Category 6A",
            "@id": "dtmi:com:syyclops:TwistedPairCableConnector:category6A;1"
          },
          {
            "name": "category7",
            "displayName": {
              "en": "Category 7"
            },
            "enumValue": "Category 7",
            "@id": "dtmi:com:syyclops:TwistedPairCableConnector:category7;1"
          },
          {
            "name": "category8",
            "displayName": {
              "en": "Category 8"
            },
            "enumValue": "Category 8",
            "@id": "dtmi:com:syyclops:TwistedPairCableConnector:category8;1"
          }
        ],
        "valueSchema": "string",
        "@id": "dtmi:com:syyclops:TwistedPairCableConnector:ES1;1"
      },
      "writable": true,
      "@id": "dtmi:com:syyclops:TwistedPairCableConnector:categoryRating;1"
    }
  ],
  "@context": [
    "dtmi:dtdl:context;3"
  ]
}