{
  "@id": "dtmi:com:syyclops:PreconditionedMinOutsideAirDamper;1",
  "@type": "Interface",
  "displayName": {
    "en": "Preconditioned Min Outside Air Damper"
  },
  "description": {
    "en": "A minimum OA damper that is used to control the flow of outside air that has been preconditioned, typically by a DOAS, prior to entering the inlet of an air handling unit or HVAC system."
  },
  "extends" : [
    "dtmi:com:syyclops:MinOutsideAirDamper;1"
  ],
  "contents": [
  ],
  "@context": [
    "dtmi:dtdl:context;3"
  ]
}
