{
  "@id": "dtmi:com:syyclops:Chiller;1",
  "@type": "Interface",
  "displayName": {
    "en": "Chiller"
  },
  "extends": [
    "dtmi:com:syyclops:HVACEquipment;1"
  ],
  "contents": [
    {
      "@type": "Component",
      "displayName": {
        "en": "Evaporator"
      },
      "name": "evaporator",
      "schema": "dtmi:com:syyclops:Evaporator;1",
      "@id": "dtmi:com:syyclops:Chiller:evaporator;1"
    },
    {
      "@type": "Component",
      "displayName": {
        "en": "Compressor"
      },
      "name": "compressor",
      "schema": "dtmi:com:syyclops:Compressor;1",
      "@id": "dtmi:com:syyclops:Chiller:compressor;1"
    },
    {
      "@type": "Property",
      "displayName": {
        "en": "Refrigerant Type"
      },
      "name": "refrigerantType",
      "schema": "string",
      "writable": true,
      "@id": "dtmi:com:syyclops:Chiller:refrigerantType;1"
    },
    {
      "@type": [
        "Property",
        "EnergyRate"
      ],
      "displayName": {
        "en": "Nominal Cooling Capacity"
      },
      "name": "nominalCoolingCapacity",
      "schema": "double",
      "unit": "britishThermalUnitPerHour",
      "writable": true,
      "@id": "dtmi:com:syyclops:Chiller:nominalCoolingCapacity;1"
    },
    {
      "@type": [
        "Property",
        "ValueAnnotation",
        "Override"
      ],
      "displayName": {
        "en": "Nominal Cooling Capacity Unit"
      },
      "name": "nominalCoolingCapacityUnit",
      "annotates": "nominalCoolingCapacity",
      "overrides": "unit",
      "schema": "PowerUnit",
      "writable": true,
      "@id": "dtmi:com:syyclops:Chiller:nominalCoolingCapacityUnit;1"
    },
    {
      "@type": [
        "Property",
        "EnergyRate"
      ],
      "displayName": {
        "en": "Net Sensible Cooling Capacity"
      },
      "name": "netSensibleCoolingCapacity",
      "schema": "double",
      "unit": "britishThermalUnitPerHour",
      "writable": true,
      "@id": "dtmi:com:syyclops:Chiller:netSensibleCoolingCapacity;1"
    },
    {
      "@type": [
        "Property",
        "ValueAnnotation",
        "Override"
      ],
      "displayName": {
        "en": "Net Sensible Cooling Capacity Unit"
      },
      "name": "netSensibleCoolingCapacityUnit",
      "annotates": "netSensibleCoolingCapacity",
      "overrides": "unit",
      "schema": "PowerUnit",
      "writable": true,
      "@id": "dtmi:com:syyclops:Chiller:netSensibleCoolingCapacityUnit;1"
    },
    {
      "@type": [
        "Property",
        "EnergyRate"
      ],
      "displayName": {
        "en": "Design Cooling Capacity"
      },
      "name": "designCoolingCapacity",
      "schema": "double",
      "unit": "britishThermalUnitPerHour",
      "writable": true,
      "@id": "dtmi:com:syyclops:Chiller:designCoolingCapacity;1"
    },
    {
      "@type": [
        "Property",
        "ValueAnnotation",
        "Override"
      ],
      "displayName": {
        "en": "Design Cooling Capacity Unit"
      },
      "name": "designCoolingCapacityUnit",
      "annotates": "designCoolingCapacity",
      "overrides": "unit",
      "schema": "PowerUnit",
      "writable": true,
      "@id": "dtmi:com:syyclops:Chiller:designCoolingCapacityUnit;1"
    },
    {
      "@type": "Property",
      "displayName": {
        "en": "Design KW/Ton"
      },
      "name": "designKWPerTon",
      "schema": "double",
      "writable": true,
      "@id": "dtmi:com:syyclops:Chiller:designKWPerTon;1"
    },
    {
      "@type": "Property",
      "displayName": {
        "en": "Design Coefficient Of Performance (COP)"
      },
      "name": "designCoefficientOfPerformance",
      "schema": "double",
      "writable": true,
      "@id": "dtmi:com:syyclops:Chiller:designCoefficientOfPerformance;1"
    },
    {
      "@type": "Property",
      "displayName": {
        "en": "Design Energy Efficiency Ratio (EER)"
      },
      "name": "designEnergyEfficiencyRatio",
      "schema": "double",
      "writable": true,
      "@id": "dtmi:com:syyclops:Chiller:designEnergyEfficiencyRatio;1"
    },
    {
      "@type": "Property",
      "displayName": {
        "en": "Nominal KW/Ton"
      },
      "name": "nominalKWPerTon",
      "schema": "double",
      "writable": true,
      "@id": "dtmi:com:syyclops:Chiller:nominalKWPerTon;1"
    },
    {
      "@type": "Property",
      "displayName": {
        "en": "Nominal Coefficient Of Performance (COP)"
      },
      "name": "nominalCoefficientOfPerformance",
      "schema": "double",
      "writable": true,
      "@id": "dtmi:com:syyclops:Chiller:nominalCoefficientOfPerformance;1"
    },
    {
      "@type": "Property",
      "displayName": {
        "en": "Nominal Energy Efficiency Ratio (EER)"
      },
      "name": "nominalEnergyEfficiencyRatio",
      "schema": "double",
      "writable": true,
      "@id": "dtmi:com:syyclops:Chiller:nominalEnergyEfficiencyRatio;1"
    }
  ],
  "@context": [
    "dtmi:dtdl:context;3",
    "dtmi:dtdl:extension:quantitativeTypes;1",
    "dtmi:dtdl:extension:annotation;1",
    "dtmi:dtdl:extension:overriding;1"
  ]
}